csvtotable/cli.py
csvtotable/convert.py
csvtotable/logger.py
csvtotable/templates/template.j2
csvtotablenameless-3.0.2.0.dist-info/METADATA
csvtotablenameless-3.0.2.0.dist-info/WHEEL
csvtotablenameless-3.0.2.0.dist-info/entry_points.txt
csvtotablenameless-3.0.2.0.dist-info/licenses/LICENSE
csvtotablenameless-3.0.2.0.dist-info/RECORD
