Metadata-Version: 2.4
Name: CSVtoTableNameless
Version: 3.0.2.0
Summary: Simple commandline utility to convert CSV files to searchable and sortable HTML table.
Project-URL: Download, https://github.com/NanashiTheNameless/csvtotable/releases/latest
Project-URL: Homepage, https://github.com/NanashiTheNameless/csvtotable
Project-URL: GitHub-Sponsor, https://github.com/sponsors/NanashiTheNameless
Project-URL: BuyMeACoffee, https://buymeacoffee.com/NamelessNanashi
Author: NanashiTheNameless
Author-email: NanashiTheNameless <NanashiTheNameless@NamelessNanashi.dev>
Maintainer: NanashiTheNameless
Maintainer-email: NanashiTheNameless <NanashiTheNameless@NamelessNanashi.dev>
License-Expression: MIT
License-File: LICENSE
Classifier: Development Status :: 4 - Beta
Classifier: Intended Audience :: Developers
Classifier: License :: OSI Approved :: MIT License
Classifier: Natural Language :: English
Classifier: Programming Language :: Python
Classifier: Programming Language :: Python :: 3
Classifier: Programming Language :: Python :: 3 :: Only
Classifier: Programming Language :: Python :: 3.10
Classifier: Programming Language :: Python :: 3.11
Classifier: Programming Language :: Python :: 3.12
Classifier: Programming Language :: Python :: 3.13
Classifier: Programming Language :: Python :: 3.14
Requires-Python: >=3.10
Requires-Dist: colorama>=0.4.6
Requires-Dist: jinja2>=3.1.6
Requires-Dist: six>=1.17
Requires-Dist: unicodecsv>=0.14.1
